{
	"summary": {
		"siteInquiryType": "detail",
		"siteType": "drt",
		"coordinate": {
			"x": "127.2613444",
			"y": "35.9887776",
			"mapZoomLevel": "12",
			"isExactPosition": true
		},
		"id": "1064059079",
		"name": "놀토피아",
		"address": "전라북도 완주군 고산면 소향리 162",
		"addressAbbr": "소향리 162",
		"roadAddr": {
			"text": "전라북도 완주군 고산면 대아저수로 416",
			"abbrText": "대아저수로 416"
		},
		"isPollingPlace": false,
		"isRestaurant": false,
		"isHairshop": false,
		"isPlaceAttraction": false,
		"isAccommodation": false,
		"phone": "070-4100-1100",
		"virtualPhone": "0507-1358-1100",
		"phoneOrigin": "070-4100-1100",
		"isCallLink": false,
		"callLinkKey": "3b515c50235caa63e3b8a181024e7fc8",
		"isPremium": false,
		"category": "스포츠,오락 &gt; 암벽등반",
		"twoDepthCategory": "스포츠,오락 &gt; 암벽등반",
		"lastCategory": "암벽등반",
		"josaForLastCategory": "을",
		"cid": "222037",
		"homepageList": [
			{
				"url": "http://www.noltopia.com",
				"landingUrl": "http://www.noltopia.com",
				"korName": "공식",
				"type": "normal",
				"mUrl": "http://www.noltopia.com",
				"mLandingUrl": "http://www.noltopia.com",
				"className": "official",
				"isRepresent": true,
				"isDeadUrl": false
			}
		],
		"description": "",
		"detailedDescription": "체험자의 심신을 발달을 위한 클라이밍존 / 스크린존 / 키즈존 34종 완비\n\n※ 이용객을 위한 시설 ※ \n1.  이용객의 귀중품을 보관하기 위한 사물함 마련 무료\n    (열쇠 분실시 5천원)\n2. 2층 대기자 및 이용자들을 위한 휴식공간 마련(가져온 간단한 음식료 취식 가능/국물류 제외) - (음식료는 판매하지 않습니다.)\n    \n※ 이용객 주의사항 ※ \n1. 음식물은 1층 놀이시설 내부 반입을 금지합니다.\n2. 운동화를 제외한 구두, 장화, 축구화, 슬리퍼 등은 시설이용에 제한됩니다.\n3. 시설 이용객들을 위해 애완동물은 출입할 수 없습니다.\n4. 귀걸이, 시계, 반지, 주머니에서 떨어 질 수 있는 무거운 물건(예 : 스마트폰) 등은 사물함에 보관하는 것을 권장합니다.  \n    (권장사항에 위배되는 행위는 사고 발생의 원인으로 법적 보호를 받을 수 없습니다.) \n5. 매 회차별 시간은 20~ 45분 까지이므로 사전에 도착하셔야 합니다.\n    (주말의 경우 조기마감이 될 수 있으므로 사전 전화문의 바랍니다.(☎ 070-4100-1100))\n    5-1. 매 회차별 10분에서 20분 전 안전교육을 실시하오니, (안전요원 안내방송)\n6. 시설이용제한 (안전요원은 시설지역별 위치하여 이용객의 시설이용에 대한 도움을 제공하나, 1:1 보호는 불가능합니다.)\n    6-1. 7세 이상의 이용객(전 시설 사용가능) \n    6-2. 6세 이하의 이용객(키즈존 만 사용가능) \n    6-3. 6~5세 이용객(전 시설 이용시) - 보호자가 1:1 보호 필수\n    6-4. 주말의 경우 이용객 증가 / 특수적 보호가 필요한 이용객 / 내 아이의 성격 등의 원인으로 인해 특별한 보호가 필하다고 판단되는 경우 \n           (보호자가 1:1 보호 필수)\n    6-5. 위에 해당되는 모든 보호자는 발권 후 장비착용을 필히 하셔야 합니다. (6-2의 이용객 보호자 제외 : 단, 정글짐내에서만 가능)\n7. 1층 시설내부의 포토타임(무료관람시간)은 공공의 질서유지를 위해 제공하지 않습니다.\n    (2층 휴식공간에서 관람 가능) \n8. 시설내부에 부착된 주의사항/안전수칙은 반드시 지켜주시기 바랍니다.\n    (부착물 내용 불이행으로 인한 사고는 책임지지 않습니다.)\n9. 안전요원의 지시 불응시 시설내부 질서를 위해 퇴장조치 될 수 있습니다.",
		"descriptionForMobile": "체험자의 심신을 발달을 위한 클라이밍존 / 스크린존 /...",
		"moreDescriptionBtnForMobile": true,
		"moreDetailedDescription": "",
		"moreDetailedDescriptionUrl": "",
		"road": "구주소 : 전라북도 완주군 소향리 162번지(대아저수지 방면)\n신주소 : 고산면 대아저수지로 416",
		"infoSource": "",
		"infoSourceUrl": "",
		"targetUrl": "",
		"mobileTargetUrl": "",
		"hasPoint": false,
		"hasReview": false,
		"isUserEditCheck": false,
		"repKeywordList": [
			"클라이밍",
			"어린이체험학습",
			"유치원체험학습",
			"현장체험학습"
		],
		"brandDirNum": null,
		"naverTalktalkUrlForPc": null,
		"naverTalktalkUrlForMobile": null,
		"isNailshop": false,
		"isHospital": false,
		"isNaverhotel": false
	},
	"bizHours": {
		"bizHourList": [
			{
				"type": "매일",
				"startTime": "00:00",
				"endTime": "00:00",
				"isDayOff": true,
				"description": "",
				"outer-class": {
					"bizHourList": null
				}
			}
		]
	},
	"options": {
		"optionList": [
			{
				"id": "13",
				"name": "단체석",
				"desc": null,
				"outer-class": {
					"optionList": null,
					"optionDescList": null
				}
			},
			{
				"id": "2",
				"name": "주차",
				"desc": null,
				"outer-class": {
					"optionList": null,
					"optionDescList": null
				}
			},
			{
				"id": "1",
				"name": "예약",
				"desc": null,
				"outer-class": {
					"optionList": null,
					"optionDescList": null
				}
			},
			{
				"id": "6",
				"name": "유아시설(놀이방)",
				"desc": null,
				"outer-class": {
					"optionList": null,
					"optionDescList": null
				}
			},
			{
				"id": "8",
				"name": "남/녀 화장실 구분",
				"desc": null,
				"outer-class": {
					"optionList": null,
					"optionDescList": null
				}
			}
		],
		"optionDescList": []
	},
	"images": {
		"imageList": [
			{
				"type": "DRT",
				"number": "1",
				"url": "/놀토피아_main0_.jpg",
				"source": null,
				"desc": "",
				"ugcInfo": null,
				"modDate": "2020-01-14 23:48:07",
				"moreImageUrlForPC": null,
				"moreImageUrlForMobile": null,
				"nclickForPC": null,
				"tabName": "baseInfo",
				"hideProviderText": false,
				"outer-class": {
					"imageList": null
				}
			},
			{
				"type": "DRT",
				"number": "2",
				"url": "/놀토피아_main1_.jpg",
				"source": null,
				"desc": "",
				"ugcInfo": null,
				"modDate": "2020-01-14 23:48:07",
				"moreImageUrlForPC": null,
				"moreImageUrlForMobile": null,
				"nclickForPC": null,
				"tabName": "baseInfo",
				"hideProviderText": false,
				"outer-class": {
					"imageList": null
				}
			},
			{
				"type": "DRT",
				"number": "3",
				"url": "/놀토피아_main2_.jpg",
				"source": null,
				"desc": "",
				"ugcInfo": null,
				"modDate": "2020-01-14 23:48:07",
				"moreImageUrlForPC": null,
				"moreImageUrlForMobile": null,
				"nclickForPC": null,
				"tabName": "baseInfo",
				"hideProviderText": false,
				"outer-class": {
					"imageList": null
				}
			},
			{
				"type": "DRT",
				"number": "4",
				"url": "/놀토피아_main3_.jpg",
				"source": null,
				"desc": "",
				"ugcInfo": null,
				"modDate": "2020-01-14 23:48:07",
				"moreImageUrlForPC": null,
				"moreImageUrlForMobile": null,
				"nclickForPC": null,
				"tabName": "baseInfo",
				"hideProviderText": false,
				"outer-class": {
					"imageList": null
				}
			},
			{
				"type": "DRT",
				"number": "5",
				"url": "/놀토피아_main4_.jpg",
				"source": null,
				"desc": "",
				"ugcInfo": null,
				"modDate": "2020-01-14 23:48:07",
				"moreImageUrlForPC": null,
				"moreImageUrlForMobile": null,
				"nclickForPC": null,
				"tabName": "baseInfo",
				"hideProviderText": false,
				"outer-class": {
					"imageList": null
				}
			}
		]
	},
	"menus": {
		"menuImage": null,
		"menuList": [
			{
				"name": "1시간권(성인/평일)",
				"price": "7,000원",
				"isRecommended": false,
				"change": false,
				"outer-class": {
					"menuImage": null,
					"menuList": null
				}
			},
			{
				"name": "1시간권(성인/주말)",
				"price": "9,000원",
				"isRecommended": false,
				"change": false,
				"outer-class": {
					"menuImage": null,
					"menuList": null
				}
			},
			{
				"name": "1시간권(어린이·청소년/평일)",
				"price": "6,000원",
				"isRecommended": false,
				"change": false,
				"outer-class": {
					"menuImage": null,
					"menuList": null
				}
			},
			{
				"name": "1시간권(어린이·청소년/주말)",
				"price": "8,000원",
				"isRecommended": false,
				"change": false,
				"outer-class": {
					"menuImage": null,
					"menuList": null
				}
			},
			{
				"name": "슬라이드 이용권(평일)",
				"price": "1,500원",
				"isRecommended": false,
				"change": false,
				"outer-class": {
					"menuImage": null,
					"menuList": null
				}
			},
			{
				"name": "슬라이드 이용권(주말)",
				"price": "2,000원",
				"isRecommended": false,
				"change": false,
				"outer-class": {
					"menuImage": null,
					"menuList": null
				}
			}
		]
	},
	"menuImages": {
		"menuImageList": [
			{
				"type": "drt",
				"imageUrl": "http://ldb.phinf.naver.net/20190107_40/1546786819980pOa1M_JPEG/1z-Wuw48eKS2KSH1htCT9Hn8.jpg",
				"postUrl": null,
				"score": null,
				"updateDate": "2020-04-19 13:17:43",
				"source": null
			}
		]
	},
	"coupon": {
		"isShow": false,
		"url": "",
		"mobileUrl": ""
	},
	"subphones": {
		"count": "0",
		"subphoneList": []
	},
	"relateInfos": {
		"relateInfoList": []
	},
	"searchInterlock": {
		"TRUE": "1",
		"keyword": "e11cfe4d15a7ebbf10f1ff9b8935291e67f074f311a321cb5a6290040ce8afe49554d8488c2dbf8225cd80a3f4d816108b6c4460214507bc4af3e6aabb1153935549bd02035fe1f90d7d4363f6cb97e7",
		"blog": "1",
		"cafe": "1"
	},
	"streetPanorama": {
		"id": "fVARNZTBM9ALSM8LaHQEow==",
		"pan": "156.48",
		"tilt": "10",
		"lng": "127.261173",
		"lat": "35.98917",
		"fov": "120"
	},
	"skyPanorama": {
		"id": "",
		"pan": "0.0",
		"tilt": "0.0",
		"lng": "0.0",
		"lat": "0.0",
		"fov": "0"
	},
	"insidePanorama": {
		"id": "",
		"pan": "0.0",
		"tilt": "0.0",
		"lng": "0.0",
		"lat": "0.0",
		"fov": "0"
	},
	"interiorPanorama": {
		"id": "",
		"pan": "0.0",
		"tilt": "0.0",
		"lng": "0.0",
		"lat": "0.0",
		"fov": "0"
	},
	"indoorPanorama": {
		"id": "",
		"pan": "0.0",
		"tilt": "0.0",
		"lng": "0.0",
		"lat": "0.0",
		"fov": "0"
	},
	"indoor": {
		"floor": "",
		"underGmid": null,
		"underMid": "0"
	},
	"theme": null,
	"themeDetail": null,
	"editButtons": {
		"editButtonList": [
			{
				"name": "정보수정 제안",
				"type": "report",
				"url": "\n\t\thttps://report.map.naver.com/form.nhn\n\t",
				"nclicksName": "wronginfo",
				"outer-class": {
					"editButtonList": null
				}
			},
			{
				"name": "통계",
				"type": "stats",
				"url": "https://submit.naver.com/checkLoginType.nhn",
				"nclicksName": "stats",
				"outer-class": {
					"editButtonList": null
				}
			}
		]
	},
	"poi": {
		"poi_info": {
			"road": {
				"poiShapeType": "1",
				"shapeKey": null,
				"boundary": null,
				"detail": null
			},
			"hasRoad": false,
			"land": null,
			"hasLand": false,
			"polygon": null,
			"hasPolygon": false
		},
		"entrance_coord": {
			"ENTRANCE_COORD_FIELD_SIZE": 7,
			"entranceCoords": [
				{
					"isRepresentative": "1",
					"coordType": "5",
					"entranceCoordX": "127.2610900",
					"entranceCoordY": "35.9891540",
					"coordSubType": 1
				}
			]
		}
	},
	"thumbnail": {
		"number": "0",
		"url": "http://ldb.phinf.naver.net/20200114_122/1579012989314CPRRz_JPEG/93uhdLghOFsL1C6Queom9QGv.jpg",
		"source": null,
		"imageTabName": "baseInfo",
		"modDate": null,
		"hasMore": true
	},
	"cpDetail": {
		"nadleDetail": null,
		"citymapDetail": null,
		"baeminDetail": null,
		"onnuriDetail": null,
		"campingzoneDetail": null,
		"parkingModuDetail": null,
		"toiletDetail": null,
		"naverBookingDetail": null,
		"uokDetail": null,
		"hiraDetail": null,
		"tvcastDetail": null,
		"shopwindowDetail": null,
		"yogiyoDetail": null,
		"cescoDetail": null,
		"golfzonDetail": null,
		"opinetDetail": null,
		"yanoljaDetail": null,
		"goodchoiceDetail": null,
		"yeogiyaDetail": null,
		"naverhotelDetail": null,
		"cpMenuList": [
			"DEFAULT"
		],
		"relatedLinks": {
			"relatedLinkList": []
		},
		"michelinGuide": null,
		"kozazaDetail": null,
		"heybeautyDetail": null
	},
	"card": {
		"hasBenefit": false
	},
	"hairshop": null
}