{
	"summary": {
		"siteInquiryType": "detail",
		"siteType": "drt",
		"coordinate": {
			"x": "128.96707808500705",
			"y": "35.10882067596241",
			"mapZoomLevel": "12",
			"isExactPosition": true
		},
		"id": "37427021",
		"name": "락오디세이 하단점",
		"address": "부산광역시 사하구 하단동 510-9",
		"addressAbbr": "하단동 510-9",
		"roadAddr": {
			"text": "부산광역시 사하구 낙동대로 498",
			"abbrText": "낙동대로 498"
		},
		"isPollingPlace": false,
		"isRestaurant": false,
		"isHairshop": false,
		"isPlaceAttraction": false,
		"isAccommodation": false,
		"phone": "010-4915-5158",
		"virtualPhone": "",
		"phoneOrigin": "010-4915-5158",
		"isCallLink": false,
		"callLinkKey": "a66028c6b8fcee641a5671e0c16d3d76",
		"isPremium": false,
		"category": "스포츠,오락 &gt; 암벽등반",
		"twoDepthCategory": "스포츠,오락 &gt; 암벽등반",
		"lastCategory": "암벽등반",
		"josaForLastCategory": "을",
		"cid": "222037",
		"homepageList": [
			{
				"url": "http://rockodyssey0.modoo.at/?link=3yffhqt3",
				"landingUrl": "http://rockodyssey0.modoo.at/?link=3yffhqt3",
				"korName": "모두",
				"type": "modoo",
				"mUrl": "http://rockodyssey0.modoo.at/?link=3yffhqt3",
				"mLandingUrl": "http://rockodyssey0.modoo.at/?link=3yffhqt3",
				"className": "modoo",
				"isRepresent": true,
				"isDeadUrl": false
			},
			{
				"url": "http://cafe.naver.com/rockodyssey",
				"landingUrl": "http://cafe.naver.com/rockodyssey",
				"korName": "카페",
				"type": "cafe",
				"mUrl": "http://cafe.naver.com/rockodyssey",
				"mLandingUrl": "http://cafe.naver.com/rockodyssey",
				"className": "cafe",
				"isRepresent": false,
				"isDeadUrl": false
			},
			{
				"url": "http://blog.naver.com/cinepol",
				"landingUrl": "http://blog.naver.com/cinepol",
				"korName": "블로그",
				"type": "blog",
				"mUrl": "http://blog.naver.com/cinepol",
				"mLandingUrl": "http://blog.naver.com/cinepol",
				"className": "blog",
				"isRepresent": false,
				"isDeadUrl": false
			}
		],
		"description": "",
		"detailedDescription": "부산클라이밍,부산실내암벽,사하구클라이밍. 140평 부산최대 규모, 유아 놀이벽, 샤워실,탈의실, 1:1강습, 웨이트, 다이어트 컨설팅",
		"descriptionForMobile": "부산클라이밍,부산실내암벽,사하구클라이밍. 140평 부산...",
		"moreDescriptionBtnForMobile": true,
		"moreDetailedDescription": "",
		"moreDetailedDescriptionUrl": "",
		"road": "하단역9번 출구 - 동아대 방향 - 탑마트 2층. 지하주차장 무료 이용.",
		"infoSource": "",
		"infoSourceUrl": "",
		"targetUrl": "",
		"mobileTargetUrl": "",
		"hasPoint": false,
		"hasReview": false,
		"isUserEditCheck": false,
		"repKeywordList": [
			"클라이밍",
			"실내암벽"
		],
		"brandDirNum": null,
		"naverTalktalkUrlForPc": null,
		"naverTalktalkUrlForMobile": null,
		"isNailshop": false,
		"isHospital": false,
		"isNaverhotel": false
	},
	"bizHours": {
		"bizHourList": [
			{
				"type": "평일",
				"startTime": "14:00",
				"endTime": "22:30",
				"isDayOff": false,
				"description": "",
				"outer-class": {
					"bizHourList": null
				}
			},
			{
				"type": "주말",
				"startTime": "14:00",
				"endTime": "20:00",
				"isDayOff": false,
				"description": "센터 사정으로 변경될 수도 있으니 확인 전화 부탁드립니다.",
				"outer-class": {
					"bizHourList": null
				}
			}
		]
	},
	"options": {
		"optionList": [
			{
				"id": "2",
				"name": "주차",
				"desc": null,
				"outer-class": {
					"optionList": null,
					"optionDescList": null
				}
			},
			{
				"id": "1",
				"name": "예약",
				"desc": null,
				"outer-class": {
					"optionList": null,
					"optionDescList": null
				}
			},
			{
				"id": "6",
				"name": "유아시설(놀이방)",
				"desc": null,
				"outer-class": {
					"optionList": null,
					"optionDescList": null
				}
			},
			{
				"id": "8",
				"name": "남/녀 화장실 구분",
				"desc": null,
				"outer-class": {
					"optionList": null,
					"optionDescList": null
				}
			}
		],
		"optionDescList": []
	},
	"images": {
		"imageList": [
			{
				"type": "DRT",
				"number": "1",
				"url": "/락오디세이 하단점_main0_.jpg",
				"source": null,
				"desc": "",
				"ugcInfo": null,
				"modDate": "2017-08-09 04:28:02",
				"moreImageUrlForPC": null,
				"moreImageUrlForMobile": null,
				"nclickForPC": null,
				"tabName": "baseInfo",
				"hideProviderText": false,
				"outer-class": {
					"imageList": null
				}
			},
			{
				"type": "DRT",
				"number": "2",
				"url": "/락오디세이 하단점_main1_.jpg",
				"source": null,
				"desc": "",
				"ugcInfo": null,
				"modDate": "2017-08-09 04:28:02",
				"moreImageUrlForPC": null,
				"moreImageUrlForMobile": null,
				"nclickForPC": null,
				"tabName": "baseInfo",
				"hideProviderText": false,
				"outer-class": {
					"imageList": null
				}
			},
			{
				"type": "DRT",
				"number": "3",
				"url": "/락오디세이 하단점_main2_.jpg",
				"source": null,
				"desc": "",
				"ugcInfo": null,
				"modDate": "2017-08-09 04:28:02",
				"moreImageUrlForPC": null,
				"moreImageUrlForMobile": null,
				"nclickForPC": null,
				"tabName": "baseInfo",
				"hideProviderText": false,
				"outer-class": {
					"imageList": null
				}
			},
			{
				"type": "DRT",
				"number": "4",
				"url": "/락오디세이 하단점_main3_.jpg",
				"source": null,
				"desc": "",
				"ugcInfo": null,
				"modDate": "2017-08-09 04:28:02",
				"moreImageUrlForPC": null,
				"moreImageUrlForMobile": null,
				"nclickForPC": null,
				"tabName": "baseInfo",
				"hideProviderText": false,
				"outer-class": {
					"imageList": null
				}
			},
			{
				"type": "DRT",
				"number": "5",
				"url": "/락오디세이 하단점_main4_.jpg",
				"source": null,
				"desc": "",
				"ugcInfo": null,
				"modDate": "2017-08-09 04:28:02",
				"moreImageUrlForPC": null,
				"moreImageUrlForMobile": null,
				"nclickForPC": null,
				"tabName": "baseInfo",
				"hideProviderText": false,
				"outer-class": {
					"imageList": null
				}
			}
		]
	},
	"menus": {
		"menuImage": null,
		"menuList": []
	},
	"menuImages": {
		"menuImageList": []
	},
	"coupon": {
		"isShow": false,
		"url": "",
		"mobileUrl": ""
	},
	"subphones": {
		"count": "0",
		"subphoneList": []
	},
	"relateInfos": {
		"relateInfoList": []
	},
	"searchInterlock": {
		"TRUE": "1",
		"keyword": "fb6b87016bb59e12641d0ef4902c766e6fd78ccdf0b3398e79f3e93a673f92ea1ad3b98c87b5909a155f7470f7818443cc5a9369702e69e181c63543b032e1d6d4ed24f3a029577bed3558b0e9066d1f920de268db1f99da0dec9a803dc6cb1520806676aaaaa193cfe28222882e7d42",
		"blog": "1",
		"cafe": "1"
	},
	"streetPanorama": {
		"id": "jBQQoRimqvUz7pk5AxrqkQ==",
		"pan": "14.19",
		"tilt": "27.25",
		"lng": "128.9669468",
		"lat": "35.1086455",
		"fov": "35"
	},
	"skyPanorama": {
		"id": "mBreWzeUpsm+N0JBCXJcjQ==",
		"pan": "-79.28",
		"tilt": "-30",
		"lng": "128.9676056",
		"lat": "35.1087303",
		"fov": "124"
	},
	"insidePanorama": {
		"id": "",
		"pan": "0.0",
		"tilt": "0.0",
		"lng": "0.0",
		"lat": "0.0",
		"fov": "0"
	},
	"interiorPanorama": {
		"id": "",
		"pan": "0.0",
		"tilt": "0.0",
		"lng": "0.0",
		"lat": "0.0",
		"fov": "0"
	},
	"indoorPanorama": {
		"id": "",
		"pan": "0.0",
		"tilt": "0.0",
		"lng": "0.0",
		"lat": "0.0",
		"fov": "0"
	},
	"indoor": {
		"floor": "",
		"underGmid": null,
		"underMid": "0"
	},
	"theme": null,
	"themeDetail": null,
	"editButtons": {
		"editButtonList": [
			{
				"name": "정보수정 제안",
				"type": "report",
				"url": "\n\t\thttps://report.map.naver.com/form.nhn\n\t",
				"nclicksName": "wronginfo",
				"outer-class": {
					"editButtonList": null
				}
			},
			{
				"name": "통계",
				"type": "stats",
				"url": "https://submit.naver.com/checkLoginType.nhn",
				"nclicksName": "stats",
				"outer-class": {
					"editButtonList": null
				}
			}
		]
	},
	"poi": {
		"poi_info": {
			"road": {
				"poiShapeType": "1",
				"shapeKey": null,
				"boundary": null,
				"detail": null
			},
			"hasRoad": false,
			"land": null,
			"hasLand": false,
			"polygon": null,
			"hasPolygon": false
		},
		"entrance_coord": {
			"ENTRANCE_COORD_FIELD_SIZE": 7,
			"entranceCoords": [
				{
					"isRepresentative": "1",
					"coordType": "5",
					"entranceCoordX": "128.9669910",
					"entranceCoordY": "35.1087590",
					"coordSubType": 1
				}
			]
		}
	},
	"thumbnail": {
		"number": "0",
		"url": "http://ldb.phinf.naver.net/20151230_105/1451452830414niB4F_JPEG/167173534330755_0.jpeg",
		"source": null,
		"imageTabName": "baseInfo",
		"modDate": null,
		"hasMore": true
	},
	"cpDetail": {
		"nadleDetail": null,
		"citymapDetail": null,
		"baeminDetail": null,
		"onnuriDetail": null,
		"campingzoneDetail": null,
		"parkingModuDetail": null,
		"toiletDetail": null,
		"naverBookingDetail": null,
		"uokDetail": null,
		"hiraDetail": null,
		"tvcastDetail": null,
		"shopwindowDetail": null,
		"yogiyoDetail": null,
		"cescoDetail": null,
		"golfzonDetail": null,
		"opinetDetail": null,
		"yanoljaDetail": null,
		"goodchoiceDetail": null,
		"yeogiyaDetail": null,
		"naverhotelDetail": null,
		"cpMenuList": [
			"DEFAULT"
		],
		"relatedLinks": {
			"relatedLinkList": []
		},
		"michelinGuide": null,
		"kozazaDetail": null,
		"heybeautyDetail": null
	},
	"card": {
		"hasBenefit": false
	},
	"hairshop": null
}