{
	"summary": {
		"siteInquiryType": "detail",
		"siteType": "drt",
		"coordinate": {
			"x": "127.0308681",
			"y": "37.2767201",
			"mapZoomLevel": "12",
			"isExactPosition": true
		},
		"id": "37093244",
		"name": "킹콩클라이밍",
		"address": "경기도 수원시 팔달구 인계동 942",
		"addressAbbr": "인계동 942",
		"roadAddr": {
			"text": "경기도 수원시 팔달구 경수대로 572",
			"abbrText": "경수대로 572"
		},
		"isPollingPlace": false,
		"isRestaurant": false,
		"isHairshop": false,
		"isPlaceAttraction": false,
		"isAccommodation": false,
		"phone": "1855-0514",
		"virtualPhone": "",
		"phoneOrigin": "1855-0514",
		"isCallLink": false,
		"callLinkKey": "7bd1dd53029d4286b6cc87ce023e7ddd",
		"isPremium": false,
		"category": "스포츠,오락 &gt; 암벽등반",
		"twoDepthCategory": "스포츠,오락 &gt; 암벽등반",
		"lastCategory": "암벽등반",
		"josaForLastCategory": "을",
		"cid": "222037",
		"homepageList": [
			{
				"url": "http://kingkongc.com/",
				"landingUrl": "http://kingkongc.com/",
				"korName": "공식",
				"type": "normal",
				"mUrl": "http://kingkongc.com/",
				"mLandingUrl": "http://kingkongc.com/",
				"className": "official",
				"isRepresent": true,
				"isDeadUrl": false
			},
			{
				"url": "http://.facebook.com/kingclimb",
				"landingUrl": "http://.facebook.com/kingclimb",
				"korName": "공식",
				"type": "facebook",
				"mUrl": "http://.facebook.com/kingclimb",
				"mLandingUrl": "http://.facebook.com/kingclimb",
				"className": "official",
				"isRepresent": false,
				"isDeadUrl": false
			},
			{
				"url": "https://www.facebook.com/kingclimb",
				"landingUrl": "https://www.facebook.com/kingclimb",
				"korName": "카페",
				"type": "cafe",
				"mUrl": "https://www.facebook.com/kingclimb",
				"mLandingUrl": "https://www.facebook.com/kingclimb",
				"className": "cafe",
				"isRepresent": false,
				"isDeadUrl": false
			}
		],
		"description": "",
		"detailedDescription": "수원 인계동에 위치한 클라이밍짐입니다.\n재미있게 놀면서 운동되는 클라이밍하러 오세요~",
		"descriptionForMobile": "수원 인계동에 위치한 클라이밍짐입니다.\n재미있게 놀면서...",
		"moreDescriptionBtnForMobile": true,
		"moreDetailedDescription": "",
		"moreDetailedDescriptionUrl": "",
		"road": "동수원사거리에서 오산방향 50m 삼성생명빌딩 좌측에 있습니다",
		"infoSource": "",
		"infoSourceUrl": "",
		"targetUrl": "",
		"mobileTargetUrl": "",
		"hasPoint": false,
		"hasReview": false,
		"isUserEditCheck": false,
		"repKeywordList": [
			"클라이밍",
			"볼더링",
			"다이어트",
			"실내암벽등반",
			"암벽등반"
		],
		"brandDirNum": null,
		"naverTalktalkUrlForPc": null,
		"naverTalktalkUrlForMobile": null,
		"isNailshop": false,
		"isHospital": false,
		"isNaverhotel": false
	},
	"bizHours": {
		"bizHourList": [
			{
				"type": "일요일",
				"startTime": "00:00",
				"endTime": "00:00",
				"isDayOff": true,
				"description": "",
				"outer-class": {
					"bizHourList": null
				}
			},
			{
				"type": "평일",
				"startTime": "11:00",
				"endTime": "23:00",
				"isDayOff": false,
				"description": "",
				"outer-class": {
					"bizHourList": null
				}
			},
			{
				"type": "토요일",
				"startTime": "11:00",
				"endTime": "20:00",
				"isDayOff": false,
				"description": "",
				"outer-class": {
					"bizHourList": null
				}
			}
		]
	},
	"options": {
		"optionList": [
			{
				"id": "1",
				"name": "예약",
				"desc": null,
				"outer-class": {
					"optionList": null,
					"optionDescList": null
				}
			},
			{
				"id": "7",
				"name": "무선 인터넷",
				"desc": null,
				"outer-class": {
					"optionList": null,
					"optionDescList": null
				}
			}
		],
		"optionDescList": []
	},
	"images": {
		"imageList": [
			{
				"type": "DRT",
				"number": "1",
				"url": "/킹콩클라이밍_main0_.jpg",
				"source": null,
				"desc": "",
				"ugcInfo": null,
				"modDate": "2017-08-09 04:25:20",
				"moreImageUrlForPC": null,
				"moreImageUrlForMobile": null,
				"nclickForPC": null,
				"tabName": "baseInfo",
				"hideProviderText": false,
				"outer-class": {
					"imageList": null
				}
			},
			{
				"type": "DRT",
				"number": "2",
				"url": "/킹콩클라이밍_main1_.jpg",
				"source": null,
				"desc": "",
				"ugcInfo": null,
				"modDate": "2017-08-09 04:25:20",
				"moreImageUrlForPC": null,
				"moreImageUrlForMobile": null,
				"nclickForPC": null,
				"tabName": "baseInfo",
				"hideProviderText": false,
				"outer-class": {
					"imageList": null
				}
			},
			{
				"type": "DRT",
				"number": "3",
				"url": "/킹콩클라이밍_main2_.jpg",
				"source": null,
				"desc": "",
				"ugcInfo": null,
				"modDate": "2017-08-09 04:25:20",
				"moreImageUrlForPC": null,
				"moreImageUrlForMobile": null,
				"nclickForPC": null,
				"tabName": "baseInfo",
				"hideProviderText": false,
				"outer-class": {
					"imageList": null
				}
			},
			{
				"type": "DRT",
				"number": "4",
				"url": "/킹콩클라이밍_main3_.jpg",
				"source": null,
				"desc": "",
				"ugcInfo": null,
				"modDate": "2017-08-09 04:25:20",
				"moreImageUrlForPC": null,
				"moreImageUrlForMobile": null,
				"nclickForPC": null,
				"tabName": "baseInfo",
				"hideProviderText": false,
				"outer-class": {
					"imageList": null
				}
			},
			{
				"type": "DRT",
				"number": "5",
				"url": "/킹콩클라이밍_main4_.jpg",
				"source": null,
				"desc": "",
				"ugcInfo": null,
				"modDate": "2017-08-09 04:25:20",
				"moreImageUrlForPC": null,
				"moreImageUrlForMobile": null,
				"nclickForPC": null,
				"tabName": "baseInfo",
				"hideProviderText": false,
				"outer-class": {
					"imageList": null
				}
			}
		]
	},
	"menus": {
		"menuImage": null,
		"menuList": [
			{
				"name": "일일이용권",
				"price": "15,000원",
				"isRecommended": false,
				"change": false,
				"outer-class": {
					"menuImage": null,
					"menuList": null
				}
			},
			{
				"name": "일일체험(일일이용+강습)",
				"price": "25,000원",
				"isRecommended": false,
				"change": false,
				"outer-class": {
					"menuImage": null,
					"menuList": null
				}
			}
		]
	},
	"menuImages": {
		"menuImageList": []
	},
	"coupon": {
		"isShow": false,
		"url": "",
		"mobileUrl": ""
	},
	"subphones": {
		"count": "0",
		"subphoneList": []
	},
	"relateInfos": {
		"relateInfoList": []
	},
	"searchInterlock": {
		"TRUE": "1",
		"keyword": "6fad828752085749e87a268ffa687cae5f2846843839f1ebb4db0c486d332fe9587b2957c7d11006861f8c26453e9b3e07e19ba5c9aac77c73fec46f6d8a60d2b743ac6ccdf5d472db3e83a2d9b814bf4af700b71cc8f9f9d001494ed0be89c43f83c88b60032c3d0ae5ceaaf63ca5e1",
		"blog": "1",
		"cafe": "1"
	},
	"streetPanorama": {
		"id": "Foj7u97WyTR+RrjvrSvZqQ==",
		"pan": "84.33",
		"tilt": "10",
		"lng": "127.0307812",
		"lat": "37.2767114",
		"fov": "120"
	},
	"skyPanorama": {
		"id": "XUMBlje64Wm27AYt5zzDzA==",
		"pan": "-174.2",
		"tilt": "-30",
		"lng": "127.0312347",
		"lat": "37.2802773",
		"fov": "124"
	},
	"insidePanorama": {
		"id": "",
		"pan": "0.0",
		"tilt": "0.0",
		"lng": "0.0",
		"lat": "0.0",
		"fov": "0"
	},
	"interiorPanorama": {
		"id": "",
		"pan": "0.0",
		"tilt": "0.0",
		"lng": "0.0",
		"lat": "0.0",
		"fov": "0"
	},
	"indoorPanorama": {
		"id": "",
		"pan": "0.0",
		"tilt": "0.0",
		"lng": "0.0",
		"lat": "0.0",
		"fov": "0"
	},
	"indoor": {
		"floor": "",
		"underGmid": null,
		"underMid": "0"
	},
	"theme": null,
	"themeDetail": null,
	"editButtons": {
		"editButtonList": [
			{
				"name": "정보수정 제안",
				"type": "report",
				"url": "\n\t\thttps://report.map.naver.com/form.nhn\n\t",
				"nclicksName": "wronginfo",
				"outer-class": {
					"editButtonList": null
				}
			},
			{
				"name": "통계",
				"type": "stats",
				"url": "https://submit.naver.com/checkLoginType.nhn",
				"nclicksName": "stats",
				"outer-class": {
					"editButtonList": null
				}
			}
		]
	},
	"poi": {
		"poi_info": {
			"road": {
				"poiShapeType": "1",
				"shapeKey": null,
				"boundary": null,
				"detail": null
			},
			"hasRoad": false,
			"land": null,
			"hasLand": false,
			"polygon": null,
			"hasPolygon": false
		},
		"entrance_coord": {
			"ENTRANCE_COORD_FIELD_SIZE": 7,
			"entranceCoords": [
				{
					"isRepresentative": "1",
					"coordType": "5",
					"entranceCoordX": "127.0308420",
					"entranceCoordY": "37.2768540",
					"coordSubType": 5
				}
			]
		}
	},
	"thumbnail": {
		"number": "0",
		"url": "http://ldb.phinf.naver.net/20150911_225/1441958379816w7EHj_JPEG/166858577932587_0.jpeg",
		"source": null,
		"imageTabName": "baseInfo",
		"modDate": null,
		"hasMore": true
	},
	"cpDetail": {
		"nadleDetail": null,
		"citymapDetail": null,
		"baeminDetail": null,
		"onnuriDetail": null,
		"campingzoneDetail": null,
		"parkingModuDetail": null,
		"toiletDetail": null,
		"naverBookingDetail": null,
		"uokDetail": null,
		"hiraDetail": null,
		"tvcastDetail": null,
		"shopwindowDetail": null,
		"yogiyoDetail": null,
		"cescoDetail": null,
		"golfzonDetail": null,
		"opinetDetail": null,
		"yanoljaDetail": null,
		"goodchoiceDetail": null,
		"yeogiyaDetail": null,
		"naverhotelDetail": null,
		"cpMenuList": [
			"DEFAULT"
		],
		"relatedLinks": {
			"relatedLinkList": []
		},
		"michelinGuide": null,
		"kozazaDetail": null,
		"heybeautyDetail": null
	},
	"card": {
		"hasBenefit": false
	},
	"hairshop": null
}